Gryd/VERSION
Gryd/__init__.py
Gryd/bng.py
Gryd/epsg.sqlite
Gryd/geodesy.py
Gryd/geohash.py
Gryd/geoid.64.so
Gryd/geoid.dll
Gryd/geoid.so
Gryd/ing.py
Gryd/mgrs.py
Gryd/proj.64.so
Gryd/proj.dll
Gryd/proj.so
Gryd/utm.py
Gryd-1.2.0.dist-info/DESCRIPTION.rst
Gryd-1.2.0.dist-info/METADATA
Gryd-1.2.0.dist-info/RECORD
Gryd-1.2.0.dist-info/WHEEL
Gryd-1.2.0.dist-info/metadata.json
Gryd-1.2.0.dist-info/top_level.txt
