Metadata-Version: 2.0
Name: Gryd
Version: 1.2.0
Summary: Efficient great circle computation and projection library for x86 or x64 platform on Windows or Ubuntu.
Home-page: http://bruno.thoorens.free.fr
Author: Bruno THOORENS
Author-email: bruno.thoorens@free.fr
License: Copyright 2015-2016, THOORENS Bruno, BSD licence
Download-URL: https://github.com/Moustikitos/gryd
Keywords: epsg,utm,mgrs,bng,ing,map,interpolation,projection,great,circle,geohash,georef,GARS,maidenhead
Platform: UNKNOWN
Classifier: Development Status :: 6 - Mature
Classifier: Environment :: Console
Classifier: Intended Audience :: Developers
Classifier: Intended Audience :: Science/Research
Classifier: License :: OSI Approved :: BSD License
Classifier: Operating System :: Microsoft :: Windows
Classifier: Operating System :: POSIX :: Linux
Classifier: Programming Language :: C
Classifier: Programming Language :: Python :: 2
Classifier: Programming Language :: Python :: 3
Classifier: Topic :: Scientific/Engineering :: GIS
Classifier: Topic :: Software Development :: Libraries :: Python Modules
